dashwebmcp/__init__.py
dashwebmcp/relay.py
dashwebmcp/assets/dash_mcp_bridge.js
dashwebmcp-0.1.1.dist-info/METADATA
dashwebmcp-0.1.1.dist-info/WHEEL
dashwebmcp-0.1.1.dist-info/top_level.txt
dashwebmcp-0.1.1.dist-info/RECORD
