Metadata-Version: 2.4
Name: dashwebmcp
Version: 0.1.1
Summary: MCP (Model Context Protocol) bridge for Dash applications - Expose any Dash page as an MCP server
Author-email: Cemberk <cemberk@example.com>
License: MIT
Project-URL: Homepage, https://github.com/Cemberk/dashwebmcp
Project-URL: Repository, https://github.com/Cemberk/dashwebmcp.git
Project-URL: Issues, https://github.com/Cemberk/dashwebmcp/issues
Keywords: mcp,dash,plotly,ai,agent,model-context-protocol
Classifier: Development Status :: 4 - Beta
Classifier: Intended Audience :: Developers
Classifier: License :: OSI Approved :: MIT License
Classifier: Programming Language :: Python :: 3
Classifier: Programming Language :: Python :: 3.9
Classifier: Programming Language :: Python :: 3.10
Classifier: Programming Language :: Python :: 3.11
Classifier: Programming Language :: Python :: 3.12
Classifier: Topic :: Software Development :: Libraries :: Python Modules
Classifier: Topic :: Scientific/Engineering :: Visualization
Requires-Python: >=3.9
Requires-Dist: starlette>=0.35.0
Provides-Extra: mcp
Requires-Dist: mcp>=1.0.0; extra == "mcp"
Provides-Extra: server
Requires-Dist: uvicorn>=0.25.0; extra == "server"
Requires-Dist: websockets>=12.0; extra == "server"
Provides-Extra: all
Requires-Dist: dashwebmcp[mcp,server]; extra == "all"
Provides-Extra: dev
Requires-Dist: pytest>=7.0.0; extra == "dev"
Requires-Dist: pytest-asyncio>=0.21.0; extra == "dev"
Requires-Dist: pytest-cov>=4.0.0; extra == "dev"
Requires-Dist: black>=23.0.0; extra == "dev"
Requires-Dist: ruff>=0.1.0; extra == "dev"
